BMI/__init__.py
BMI/bmi_processer.py
BMI/constants.py
BMI/count_overweight.py
bmi_batch_process-0.3.dist-info/LICENSE
bmi_batch_process-0.3.dist-info/METADATA
bmi_batch_process-0.3.dist-info/WHEEL
bmi_batch_process-0.3.dist-info/top_level.txt
bmi_batch_process-0.3.dist-info/RECORD
